Workbook

Sheet Read me
A1: Signal Harbor: data catalogue template
A3: What this is | B3: The output of module 2 (Baseline). It describes where the data for each KPI comes from, so module 3 can check what exists against what the KPIs need.
A4: What it is not | B4: It holds descriptions only. Never put client data, personal data, passwords or keys in this file.
A5: Order of work | B5: Start from the signed charter. Fill tab 5 (KPIs) first, then tab 1 (Sources), then tab 2 (Tables), then tab 3 (Fields) or tab 4 (Extractions).
A6: Tab 1 Sources | B6: Where data comes from: database, file drop, email, document store, manual workbook. Includes how we would connect, who owns it, and when it arrives.
A7: Tab 2 Tables | B7: The tables, files or document types each source provides (one source can have many), the KPIs each relates to, arrival time, SLA, cut-offs and connection detail.
A8: Tab 3 Fields | B8: The fields to track inside each table, which KPI each feeds, and any time bound or exception.
A9: Tab 4 Extractions | B9: For documents: the key things to read out of each document type, with the same time bounds and exceptions.
A10: Tab 5 KPIs | B10: Owners, tracking status, signatures, how many tables, fields and extractions are mapped to the KPI, and whether it is ready for module 3.
A11: The mapping | B11: Source > table > field, and each table and field points to the KPI it serves. Tab 5 counts them, so a KPI with nothing mapped is visible straight away.
A12: How sure are we | B12: Every row says: Stated by a named person, Guessed, or Unknown. A guess is fine. A blank that looks complete is not.
A13: Not tracked today | B13: If a KPI cannot be tracked now, set its tracking status, give a tentative date if there is one, name the next step or project, and have a sponsor accept it as unknown for now.
A14: Example rows | B14: Rows 5 and 6 on each tab are invented examples in grey italics. Delete them before you start.
... A18: Version | B18: Template v1, 3 October 2026. Draft for discussion; the columns may change after review.

Sheet 1 Sources
A1: 1 Sources: where the data comes from
A2: One row per source: a database, a file drop, an email, a document store, a manual workbook. Write descriptions only. Never type a password or a key here.
A3: S01, S02 ... | B3: What people call it | C3: Pick one | D3: Pick one | E3: Folder, mailbox, server, portal | F3: A named person | G3: How we would reach it | H3: Host, schema, path, address | I3: For example env:BANK_KEY. Never the secret itself | J3: Pick one | K3: Names or roles | L3: Pick one | M3: For example by noon on working days | N3: Can we get to it? | O3: A date, or leave blank | P3: System to onboard, program running, who is doing it | Q3: Stated, guessed or unknown | R3: Name | S3: Date | T3: Filled in for you | U3: Anything else
A4: Source ID | B4: Source name | C4: Source type | D4: Structured or unstructured | E4: Where it lands or lives | F4: Data owner | G4: Connection method | H4: Connection details (no passwords) | I4: Secret reference (name only) | J4: Contains personal data? | K4: Who may see it | L4: How often it arrives | M4: Expected arrival time or SLA | N4: Availability | O4: Tentative date if not available now | P4: Next step or project | Q4: How sure are we | R4: Confirmed by | S4: Date confirmed | T4: Complete? | U4: Notes
A5: S01 | B5: Bank portal | C5: Third-party portal or API | D5: Structured | E5: Bank portal, daily download | F5: Arjun | G5: File uploaded by the owner | H5: Download folder Finance/Bank | J5: No | K5: Finance team | L5: Daily | M5: By noon on working days | N5: Available now | Q5: Stated by a named person | R5: Arjun | T5: =IF(A5="","",IF(COUNTBLANK(B5:D5)+COUNTBLANK(F5:G5)+COUNTBLANK(L5)+COUNTBLANK(Q5)=0,"Complete","Missing "&(COUNTBLANK(B5:D5)+COUNTBLANK(F5:G5)+COUNTBLANK(L5)+COUNTBLANK(Q5))&" required")) | U5: EXAMPLE ROW: delete before use
A6: S02 | B6: Call notices by email | C6: Email with attachment | D6: Unstructured | E6: Shared mailbox for notices | F6: Sara | G6: Email forwarded to us | H6: Forwarding rule not yet set up | J6: Not sure | K6: Investments team | L6: Ad hoc | M6: No fixed time | N6: Can be made available | P6: Set up a forwarding rule; Sara | Q6: Guessed | T6: =IF(A6="","",IF(COUNTBLANK(B6:D6)+COUNTBLANK(F6:G6)+COUNTBLANK(L6)+COUNTBLANK(Q6)=0,"Complete","Missing "&(COUNTBLANK(B6:D6)+COUNTBLANK(F6:G6)+COUNTBLANK(L6)+COUNTBLANK(Q6))&" required")) | U6: EXAMPLE ROW: delete before use
T7: =IF(A7="","",IF(COUNTBLANK(B7:D7)+COUNTBLANK(F7:G7)+COUNTBLANK(L7)+COUNTBLANK(Q7)=0,"Complete","Missing "&(COUNTBLANK(B7:D7)+COUNTBLANK(F7:G7)+COUNTBLANK(L7)+COUNTBLANK(Q7))&" required"))
T8: =IF(A8="","",IF(COUNTBLANK(B8:D8)+COUNTBLANK(F8:G8)+COUNTBLANK(L8)+COUNTBLANK(Q8)=0,"Complete","Missing "&(COUNTBLANK(B8:D8)+COUNTBLANK(F8:G8)+COUNTBLANK(L8)+COUNTBLANK(Q8))&" required"))
T9: =IF(A9="","",IF(COUNTBLANK(B9:D9)+COUNTBLANK(F9:G9)+COUNTBLANK(L9)+COUNTBLANK(Q9)=0,"Complete","Missing "&(COUNTBLANK(B9:D9)+COUNTBLANK(F9:G9)+COUNTBLANK(L9)+COUNTBLANK(Q9))&" required"))
T10: =IF(A10="","",IF(COUNTBLANK(B10:D10)+COUNTBLANK(F10:G10)+COUNTBLANK(L10)+COUNTBLANK(Q10)=0,"Complete","Missing "&(COUNTBLANK(B10:D10)+COUNTBLANK(F10:G10)+COUNTBLANK(L10)+COUNTBLANK(Q10))&" required"))
T11: =IF(A11="","",IF(COUNTBLANK(B11:D11)+COUNTBLANK(F11:G11)+COUNTBLANK(L11)+COUNTBLANK(Q11)=0,"Complete","Missing "&(COUNTBLANK(B11:D11)+COUNTBLANK(F11:G11)+COUNTBLANK(L11)+COUNTBLANK(Q11))&" required"))
T12: =IF(A12="","",IF(COUNTBLANK(B12:D12)+COUNTBLANK(F12:G12)+COUNTBLANK(L12)+COUNTBLANK(Q12)=0,"Complete","Missing "&(COUNTBLANK(B12:D12)+COUNTBLANK(F12:G12)+COUNTBLANK(L12)+COUNTBLANK(Q12))&" required"))
T13: =IF(A13="","",IF(COUNTBLANK(B13:D13)+COUNTBLANK(F13:G13)+COUNTBLANK(L13)+COUNTBLANK(Q13)=0,"Complete","Missing "&(COUNTBLANK(B13:D13)+COUNTBLANK(F13:G13)+COUNTBLANK(L13)+COUNTBLANK(Q13))&" required"))
T14: =IF(A14="","",IF(COUNTBLANK(B14:D14)+COUNTBLANK(F14:G14)+COUNTBLANK(L14)+COUNTBLANK(Q14)=0,"Complete","Missing "&(COUNTBLANK(B14:D14)+COUNTBLANK(F14:G14)+COUNTBLANK(L14)+COUNTBLANK(Q14))&" required"))
T15: =IF(A15="","",IF(COUNTBLANK(B15:D15)+COUNTBLANK(F15:G15)+COUNTBLANK(L15)+COUNTBLANK(Q15)=0,"Complete","Missing "&(COUNTBLANK(B15:D15)+COUNTBLANK(F15:G15)+COUNTBLANK(L15)+COUNTBLANK(Q15))&" required"))
T16: =IF(A16="","",IF(COUNTBLANK(B16:D16)+COUNTBLANK(F16:G16)+COUNTBLANK(L16)+COUNTBLANK(Q16)=0,"Complete","Missing "&(COUNTBLANK(B16:D16)+COUNTBLANK(F16:G16)+COUNTBLANK(L16)+COUNTBLANK(Q16))&" required"))
T17: =IF(A17="","",IF(COUNTBLANK(B17:D17)+COUNTBLANK(F17:G17)+COUNTBLANK(L17)+COUNTBLANK(Q17)=0,"Complete","Missing "&(COUNTBLANK(B17:D17)+COUNTBLANK(F17:G17)+COUNTBLANK(L17)+COUNTBLANK(Q17))&" required"))
T18: =IF(A18="","",IF(COUNTBLANK(B18:D18)+COUNTBLANK(F18:G18)+COUNTBLANK(L18)+COUNTBLANK(Q18)=0,"Complete","Missing "&(COUNTBLANK(B18:D18)+COUNTBLANK(F18:G18)+COUNTBLANK(L18)+COUNTBLANK(Q18))&" required"))
... T204: =IF(A204="","",IF(COUNTBLANK(B204:D204)+COUNTBLANK(F204:G204)+COUNTBLANK(L204)+COUNTBLANK(Q204)=0,"Complete","Missing "&(COUNTBLANK(B204:D204)+COUNTBLANK(F204:G204)+COUNTBLANK(L204)+COUNTBLANK(Q204))&" required"))

Sheet 2 Tables
A1: 2 Tables: what arrives from each source
A2: One row per table, file or document type that comes from a source; one source can have many. Say which KPIs each one relates to. For a document (a contract, a notice), name the document type here and say what to take out of it on tab 4.
A3: T01, T02 ... | B3: From tab 1 | C3: Pick one | D3: As people know it | E3: KPI IDs from tab 5, separated by commas. Write Unknown if you do not know | F3: For example one row per account per day | G3: Pick one | H3: For example by noon | I3: Pick one | J3: For example 24 months | K3: Schema, path, folder. No passwords | L3: For example not available on bank holidays | M3: Can we get to it? | N3: A date, or leave blank | O3: What is being done about it | P3: Stated, guessed or unknown | Q3: Name | R3: Date | S3: Filled in for you | T3: Anything else
A4: Item ID | B4: Source ID | C4: Kind | D4: Name of table, file or document type | E4: Related KPIs | F4: What one row or record means | G4: How often it arrives | H4: Expected arrival time or SLA | I4: Update pattern | J4: History available | K4: Connection detail for this item | L4: Cut-off, exceptions or time bounds | M4: Availability | N4: Tentative date if not available now | O4: Next step or project | P4: How sure are we | Q4: Confirmed by | R4: Date confirmed | S4: Complete? | T4: Notes
A5: T01 | B5: S01 | C5: File | D5: statement.csv | E5: K02 | F5: One row per account per day | G5: Daily | H5: By noon | I5: Full replace | J5: 13 months | K5: Folder Finance/Bank | L5: No file on bank holidays | M5: Available now | P5: Stated by a named person | Q5: Arjun | S5: =IF(A5="","",IF(COUNTBLANK(B5:E5)+COUNTBLANK(G5)+COUNTBLANK(P5)=0,"Complete","Missing "&(COUNTBLANK(B5:E5)+COUNTBLANK(G5)+COUNTBLANK(P5))&" required")) | T5: EXAMPLE ROW: delete before use
A6: T02 | B6: S02 | C6: Document type | D6: Capital call notice | E6: K01 | F6: One document per call | G6: Ad hoc | H6: No fixed time | I6: Append only | J6: Not sure | K6: Shared mailbox | L6: Some managers send two notices for one call | M6: Can be made available | O6: Set up a forwarding rule | P6: Guessed | S6: =IF(A6="","",IF(COUNTBLANK(B6:E6)+COUNTBLANK(G6)+COUNTBLANK(P6)=0,"Complete","Missing "&(COUNTBLANK(B6:E6)+COUNTBLANK(G6)+COUNTBLANK(P6))&" required")) | T6: EXAMPLE ROW: delete before use
S7: =IF(A7="","",IF(COUNTBLANK(B7:E7)+COUNTBLANK(G7)+COUNTBLANK(P7)=0,"Complete","Missing "&(COUNTBLANK(B7:E7)+COUNTBLANK(G7)+COUNTBLANK(P7))&" required"))
S8: =IF(A8="","",IF(COUNTBLANK(B8:E8)+COUNTBLANK(G8)+COUNTBLANK(P8)=0,"Complete","Missing "&(COUNTBLANK(B8:E8)+COUNTBLANK(G8)+COUNTBLANK(P8))&" required"))
S9: =IF(A9="","",IF(COUNTBLANK(B9:E9)+COUNTBLANK(G9)+COUNTBLANK(P9)=0,"Complete","Missing "&(COUNTBLANK(B9:E9)+COUNTBLANK(G9)+COUNTBLANK(P9))&" required"))
S10: =IF(A10="","",IF(COUNTBLANK(B10:E10)+COUNTBLANK(G10)+COUNTBLANK(P10)=0,"Complete","Missing "&(COUNTBLANK(B10:E10)+COUNTBLANK(G10)+COUNTBLANK(P10))&" required"))
S11: =IF(A11="","",IF(COUNTBLANK(B11:E11)+COUNTBLANK(G11)+COUNTBLANK(P11)=0,"Complete","Missing "&(COUNTBLANK(B11:E11)+COUNTBLANK(G11)+COUNTBLANK(P11))&" required"))
S12: =IF(A12="","",IF(COUNTBLANK(B12:E12)+COUNTBLANK(G12)+COUNTBLANK(P12)=0,"Complete","Missing "&(COUNTBLANK(B12:E12)+COUNTBLANK(G12)+COUNTBLANK(P12))&" required"))
S13: =IF(A13="","",IF(COUNTBLANK(B13:E13)+COUNTBLANK(G13)+COUNTBLANK(P13)=0,"Complete","Missing "&(COUNTBLANK(B13:E13)+COUNTBLANK(G13)+COUNTBLANK(P13))&" required"))
S14: =IF(A14="","",IF(COUNTBLANK(B14:E14)+COUNTBLANK(G14)+COUNTBLANK(P14)=0,"Complete","Missing "&(COUNTBLANK(B14:E14)+COUNTBLANK(G14)+COUNTBLANK(P14))&" required"))
S15: =IF(A15="","",IF(COUNTBLANK(B15:E15)+COUNTBLANK(G15)+COUNTBLANK(P15)=0,"Complete","Missing "&(COUNTBLANK(B15:E15)+COUNTBLANK(G15)+COUNTBLANK(P15))&" required"))
S16: =IF(A16="","",IF(COUNTBLANK(B16:E16)+COUNTBLANK(G16)+COUNTBLANK(P16)=0,"Complete","Missing "&(COUNTBLANK(B16:E16)+COUNTBLANK(G16)+COUNTBLANK(P16))&" required"))
S17: =IF(A17="","",IF(COUNTBLANK(B17:E17)+COUNTBLANK(G17)+COUNTBLANK(P17)=0,"Complete","Missing "&(COUNTBLANK(B17:E17)+COUNTBLANK(G17)+COUNTBLANK(P17))&" required"))
S18: =IF(A18="","",IF(COUNTBLANK(B18:E18)+COUNTBLANK(G18)+COUNTBLANK(P18)=0,"Complete","Missing "&(COUNTBLANK(B18:E18)+COUNTBLANK(G18)+COUNTBLANK(P18))&" required"))
... S204: =IF(A204="","",IF(COUNTBLANK(B204:E204)+COUNTBLANK(G204)+COUNTBLANK(P204)=0,"Complete","Missing "&(COUNTBLANK(B204:E204)+COUNTBLANK(G204)+COUNTBLANK(P204))&" required"))

Sheet 3 Fields
A1: 3 Fields: what to track inside each table
A2: One row per field that matters, taken from a table on tab 2. Say which KPI it feeds, and write down any time bound or exception, so the later check for gaps can match it.
A3: F001, F002 ... | B3: From tab 2 | C3: Exactly as written there | D3: In your words | E3: Pick one | F3: For example YYYY-MM-DD, SGD | G3: A list or a minimum and maximum | H3: KPI ID from tab 5. If a field feeds more than one KPI, add a row for each | I3: Pick one | J3: Pick one | K3: Pick one | L3: Time bound: start date | M3: Time bound: end date | N3: When it is wrong or missing | O3: What people do about it | P3: Stated, guessed or unknown | Q3: Name | R3: Date | S3: Filled in for you | T3: Anything else
A4: Field ID | B4: Item ID | C4: Field name as in the source | D4: Business meaning | E4: Data type | F4: Format or unit | G4: Allowed values or range | H4: Feeds KPI | I4: Role in the KPI | J4: Personal data class | K4: Required? | L4: Valid from | M4: Valid to | N4: Exception or special case | O4: How the exception is handled | P4: How sure are we | Q4: Confirmed by | R4: Date confirmed | S4: Complete? | T4: Notes
A5: F001 | B5: T01 | C5: closing_balance | D5: Cash at the end of the day | E5: Number | F5: SGD | G5: Zero or more | H5: K02 | I5: Measure | J5: Neither | K5: Yes | N5: Wrong on bank holidays | O5: Use the last working day | P5: Stated by a named person | Q5: Arjun | S5: =IF(A5="","",IF(COUNTBLANK(B5:E5)+COUNTBLANK(H5)+COUNTBLANK(J5)+COUNTBLANK(P5)=0,"Complete","Missing "&(COUNTBLANK(B5:E5)+COUNTBLANK(H5)+COUNTBLANK(J5)+COUNTBLANK(P5))&" required")) | T5: EXAMPLE ROW: delete before use
A6: F002 | B6: T01 | C6: account_no | D6: Which account the balance is for | E6: Text | H6: K02 | I6: Key | J6: Sensitive to the business | K6: Yes | P6: Guessed | S6: =IF(A6="","",IF(COUNTBLANK(B6:E6)+COUNTBLANK(H6)+COUNTBLANK(J6)+COUNTBLANK(P6)=0,"Complete","Missing "&(COUNTBLANK(B6:E6)+COUNTBLANK(H6)+COUNTBLANK(J6)+COUNTBLANK(P6))&" required")) | T6: EXAMPLE ROW: delete before use
S7: =IF(A7="","",IF(COUNTBLANK(B7:E7)+COUNTBLANK(H7)+COUNTBLANK(J7)+COUNTBLANK(P7)=0,"Complete","Missing "&(COUNTBLANK(B7:E7)+COUNTBLANK(H7)+COUNTBLANK(J7)+COUNTBLANK(P7))&" required"))
S8: =IF(A8="","",IF(COUNTBLANK(B8:E8)+COUNTBLANK(H8)+COUNTBLANK(J8)+COUNTBLANK(P8)=0,"Complete","Missing "&(COUNTBLANK(B8:E8)+COUNTBLANK(H8)+COUNTBLANK(J8)+COUNTBLANK(P8))&" required"))
S9: =IF(A9="","",IF(COUNTBLANK(B9:E9)+COUNTBLANK(H9)+COUNTBLANK(J9)+COUNTBLANK(P9)=0,"Complete","Missing "&(COUNTBLANK(B9:E9)+COUNTBLANK(H9)+COUNTBLANK(J9)+COUNTBLANK(P9))&" required"))
S10: =IF(A10="","",IF(COUNTBLANK(B10:E10)+COUNTBLANK(H10)+COUNTBLANK(J10)+COUNTBLANK(P10)=0,"Complete","Missing "&(COUNTBLANK(B10:E10)+COUNTBLANK(H10)+COUNTBLANK(J10)+COUNTBLANK(P10))&" required"))
S11: =IF(A11="","",IF(COUNTBLANK(B11:E11)+COUNTBLANK(H11)+COUNTBLANK(J11)+COUNTBLANK(P11)=0,"Complete","Missing "&(COUNTBLANK(B11:E11)+COUNTBLANK(H11)+COUNTBLANK(J11)+COUNTBLANK(P11))&" required"))
S12: =IF(A12="","",IF(COUNTBLANK(B12:E12)+COUNTBLANK(H12)+COUNTBLANK(J12)+COUNTBLANK(P12)=0,"Complete","Missing "&(COUNTBLANK(B12:E12)+COUNTBLANK(H12)+COUNTBLANK(J12)+COUNTBLANK(P12))&" required"))
S13: =IF(A13="","",IF(COUNTBLANK(B13:E13)+COUNTBLANK(H13)+COUNTBLANK(J13)+COUNTBLANK(P13)=0,"Complete","Missing "&(COUNTBLANK(B13:E13)+COUNTBLANK(H13)+COUNTBLANK(J13)+COUNTBLANK(P13))&" required"))
S14: =IF(A14="","",IF(COUNTBLANK(B14:E14)+COUNTBLANK(H14)+COUNTBLANK(J14)+COUNTBLANK(P14)=0,"Complete","Missing "&(COUNTBLANK(B14:E14)+COUNTBLANK(H14)+COUNTBLANK(J14)+COUNTBLANK(P14))&" required"))
S15: =IF(A15="","",IF(COUNTBLANK(B15:E15)+COUNTBLANK(H15)+COUNTBLANK(J15)+COUNTBLANK(P15)=0,"Complete","Missing "&(COUNTBLANK(B15:E15)+COUNTBLANK(H15)+COUNTBLANK(J15)+COUNTBLANK(P15))&" required"))
S16: =IF(A16="","",IF(COUNTBLANK(B16:E16)+COUNTBLANK(H16)+COUNTBLANK(J16)+COUNTBLANK(P16)=0,"Complete","Missing "&(COUNTBLANK(B16:E16)+COUNTBLANK(H16)+COUNTBLANK(J16)+COUNTBLANK(P16))&" required"))
S17: =IF(A17="","",IF(COUNTBLANK(B17:E17)+COUNTBLANK(H17)+COUNTBLANK(J17)+COUNTBLANK(P17)=0,"Complete","Missing "&(COUNTBLANK(B17:E17)+COUNTBLANK(H17)+COUNTBLANK(J17)+COUNTBLANK(P17))&" required"))
S18: =IF(A18="","",IF(COUNTBLANK(B18:E18)+COUNTBLANK(H18)+COUNTBLANK(J18)+COUNTBLANK(P18)=0,"Complete","Missing "&(COUNTBLANK(B18:E18)+COUNTBLANK(H18)+COUNTBLANK(J18)+COUNTBLANK(P18))&" required"))
... S204: =IF(A204="","",IF(COUNTBLANK(B204:E204)+COUNTBLANK(H204)+COUNTBLANK(J204)+COUNTBLANK(P204)=0,"Complete","Missing "&(COUNTBLANK(B204:E204)+COUNTBLANK(H204)+COUNTBLANK(J204)+COUNTBLANK(P204))&" required"))

Sheet 4 Extractions
A1: 4 Extractions: what to take out of a document
A2: For unstructured data, such as a contract or a notice: the key things to read out of each document type listed on tab 2. These are what the later check for gaps will look for.
A3: X001, X002 ... | B3: From tab 2 | C3: For example due date, amount, counterparty | D3: The decision it supports | E3: KPI ID from tab 5 | F3: For example first page, table of terms | G3: For example a date, a number with currency | H3: Pick one | I3: Pick one | J3: Time bound: start date | K3: Time bound: end date | L3: When it is missing or unclear | M3: What people do about it | N3: Stated, guessed or unknown | O3: Name | P3: Date | Q3: Filled in for you | R3: Anything else
A4: Extract ID | B4: Item ID (document type) | C4: What to extract | D4: Why it matters | E4: Feeds KPI | F4: Where in the document | G4: Expected format | H4: Required? | I4: Personal data class | J4: Valid from | K4: Valid to | L4: Exception or special case | M4: How the exception is handled | N4: How sure are we | O4: Confirmed by | P4: Date confirmed | Q4: Complete? | R4: Notes
A5: X001 | B5: T02 | C5: Due date | D5: When the cash must be ready | E5: K01 | F5: Header of the notice | G5: A date | H5: Yes | I5: Neither | L5: Notice gives a month, not a day | M5: Ask the manager | N5: Guessed | Q5: =IF(A5="","",IF(COUNTBLANK(B5:C5)+COUNTBLANK(E5)+COUNTBLANK(H5:I5)+COUNTBLANK(N5)=0,"Complete","Missing "&(COUNTBLANK(B5:C5)+COUNTBLANK(E5)+COUNTBLANK(H5:I5)+COUNTBLANK(N5))&" required")) | R5: EXAMPLE ROW: delete before use
A6: X002 | B6: T02 | C6: Amount called | D6: How much cash is needed | E6: K01 | F6: Table of terms | G6: A number with currency | H6: Yes | I6: Neither | N6: Unknown | Q6: =IF(A6="","",IF(COUNTBLANK(B6:C6)+COUNTBLANK(E6)+COUNTBLANK(H6:I6)+COUNTBLANK(N6)=0,"Complete","Missing "&(COUNTBLANK(B6:C6)+COUNTBLANK(E6)+COUNTBLANK(H6:I6)+COUNTBLANK(N6))&" required")) | R6: EXAMPLE ROW: delete before use
Q7: =IF(A7="","",IF(COUNTBLANK(B7:C7)+COUNTBLANK(E7)+COUNTBLANK(H7:I7)+COUNTBLANK(N7)=0,"Complete","Missing "&(COUNTBLANK(B7:C7)+COUNTBLANK(E7)+COUNTBLANK(H7:I7)+COUNTBLANK(N7))&" required"))
Q8: =IF(A8="","",IF(COUNTBLANK(B8:C8)+COUNTBLANK(E8)+COUNTBLANK(H8:I8)+COUNTBLANK(N8)=0,"Complete","Missing "&(COUNTBLANK(B8:C8)+COUNTBLANK(E8)+COUNTBLANK(H8:I8)+COUNTBLANK(N8))&" required"))
Q9: =IF(A9="","",IF(COUNTBLANK(B9:C9)+COUNTBLANK(E9)+COUNTBLANK(H9:I9)+COUNTBLANK(N9)=0,"Complete","Missing "&(COUNTBLANK(B9:C9)+COUNTBLANK(E9)+COUNTBLANK(H9:I9)+COUNTBLANK(N9))&" required"))
Q10: =IF(A10="","",IF(COUNTBLANK(B10:C10)+COUNTBLANK(E10)+COUNTBLANK(H10:I10)+COUNTBLANK(N10)=0,"Complete","Missing "&(COUNTBLANK(B10:C10)+COUNTBLANK(E10)+COUNTBLANK(H10:I10)+COUNTBLANK(N10))&" required"))
Q11: =IF(A11="","",IF(COUNTBLANK(B11:C11)+COUNTBLANK(E11)+COUNTBLANK(H11:I11)+COUNTBLANK(N11)=0,"Complete","Missing "&(COUNTBLANK(B11:C11)+COUNTBLANK(E11)+COUNTBLANK(H11:I11)+COUNTBLANK(N11))&" required"))
Q12: =IF(A12="","",IF(COUNTBLANK(B12:C12)+COUNTBLANK(E12)+COUNTBLANK(H12:I12)+COUNTBLANK(N12)=0,"Complete","Missing "&(COUNTBLANK(B12:C12)+COUNTBLANK(E12)+COUNTBLANK(H12:I12)+COUNTBLANK(N12))&" required"))
Q13: =IF(A13="","",IF(COUNTBLANK(B13:C13)+COUNTBLANK(E13)+COUNTBLANK(H13:I13)+COUNTBLANK(N13)=0,"Complete","Missing "&(COUNTBLANK(B13:C13)+COUNTBLANK(E13)+COUNTBLANK(H13:I13)+COUNTBLANK(N13))&" required"))
Q14: =IF(A14="","",IF(COUNTBLANK(B14:C14)+COUNTBLANK(E14)+COUNTBLANK(H14:I14)+COUNTBLANK(N14)=0,"Complete","Missing "&(COUNTBLANK(B14:C14)+COUNTBLANK(E14)+COUNTBLANK(H14:I14)+COUNTBLANK(N14))&" required"))
Q15: =IF(A15="","",IF(COUNTBLANK(B15:C15)+COUNTBLANK(E15)+COUNTBLANK(H15:I15)+COUNTBLANK(N15)=0,"Complete","Missing "&(COUNTBLANK(B15:C15)+COUNTBLANK(E15)+COUNTBLANK(H15:I15)+COUNTBLANK(N15))&" required"))
Q16: =IF(A16="","",IF(COUNTBLANK(B16:C16)+COUNTBLANK(E16)+COUNTBLANK(H16:I16)+COUNTBLANK(N16)=0,"Complete","Missing "&(COUNTBLANK(B16:C16)+COUNTBLANK(E16)+COUNTBLANK(H16:I16)+COUNTBLANK(N16))&" required"))
Q17: =IF(A17="","",IF(COUNTBLANK(B17:C17)+COUNTBLANK(E17)+COUNTBLANK(H17:I17)+COUNTBLANK(N17)=0,"Complete","Missing "&(COUNTBLANK(B17:C17)+COUNTBLANK(E17)+COUNTBLANK(H17:I17)+COUNTBLANK(N17))&" required"))
Q18: =IF(A18="","",IF(COUNTBLANK(B18:C18)+COUNTBLANK(E18)+COUNTBLANK(H18:I18)+COUNTBLANK(N18)=0,"Complete","Missing "&(COUNTBLANK(B18:C18)+COUNTBLANK(E18)+COUNTBLANK(H18:I18)+COUNTBLANK(N18))&" required"))
... Q204: =IF(A204="","",IF(COUNTBLANK(B204:C204)+COUNTBLANK(E204)+COUNTBLANK(H204:I204)+COUNTBLANK(N204)=0,"Complete","Missing "&(COUNTBLANK(B204:C204)+COUNTBLANK(E204)+COUNTBLANK(H204:I204)+COUNTBLANK(N204))&" required"))

Sheet 5 KPIs
A1: 5 KPIs: owners, tracking status and readiness
A2: One row per KPI from the signed charter. Each owner signs their own part. If a KPI cannot be tracked today, say when it might be and what is being done, and a sponsor accepts that it is unknown for now.
A3: K01, K02 ... | B3: From the charter | C3: What it means, in your words | D3: From the charter | E3: From the charter | F3: A named person | G3: A named person | H3: A named person | I3: Pick one | J3: When it could be tracked | K3: Systems to onboard, programs running, who | L3: A sponsor, if not tracked today | M3: Date | N3: Date | O3: Date | P3: Date | Q3: Counted for you from tab 2 | R3: Counted for you from tab 3 | S3: Counted for you from tab 4 | T3: Filled in for you | U3: Anything else
A4: KPI ID | B4: KPI name | C4: Definition | D4: Priority | E4: Problem it serves | F4: Business owner | G4: Data owner | H4: Process owner | I4: Tracking status | J4: Tentative date | K4: Next steps or project | L4: Unknown accepted by (sponsor) | M4: Date accepted | N4: Business owner signed | O4: Data owner signed | P4: Process owner signed | Q4: Tables mapped | R4: Fields mapped | S4: Extractions mapped | T4: Ready for module 3? | U4: Notes
A5: K01 | B5: Capital calls due, by date | C5: Cash the office must provide, by due date | D5: Must | E5: Calls arrive too late | F5: Mei | G5: Sara | H5: Sara | I5: Will be tracked in future | K5: Set up intake of notices; Sara | L5: Tom | Q5: =IF(A5="","",COUNTIF('2 Tables'!$E$5:$E$204,"*"&A5&"*")) | R5: =IF(A5="","",COUNTIF('3 Fields'!$H$5:$H$204,A5)) | S5: =IF(A5="","",COUNTIF('4 Extractions'!$E$5:$E$204,A5)) | T5: =IF(A5="","",IF(AND(F5<>"",G5<>"",H5<>"",I5<>"",N5<>"",O5<>"",P5<>"",OR(I5="Tracked today",I5="Can be tracked now",AND(K5<>"",L5<>""))),"Ready","Not ready")) | U5: EXAMPLE ROW: delete before use
A6: K02 | B6: Funding capacity | C6: Cash and committed lines available over six months | D6: Must | E6: Calls arrive too late | F6: Tom | G6: Arjun | H6: Sara | I6: Can be tracked now | Q6: =IF(A6="","",COUNTIF('2 Tables'!$E$5:$E$204,"*"&A6&"*")) | R6: =IF(A6="","",COUNTIF('3 Fields'!$H$5:$H$204,A6)) | S6: =IF(A6="","",COUNTIF('4 Extractions'!$E$5:$E$204,A6)) | T6: =IF(A6="","",IF(AND(F6<>"",G6<>"",H6<>"",I6<>"",N6<>"",O6<>"",P6<>"",OR(I6="Tracked today",I6="Can be tracked now",AND(K6<>"",L6<>""))),"Ready","Not ready")) | U6: EXAMPLE ROW: delete before use
Q7: =IF(A7="","",COUNTIF('2 Tables'!$E$5:$E$204,"*"&A7&"*")) | R7: =IF(A7="","",COUNTIF('3 Fields'!$H$5:$H$204,A7)) | S7: =IF(A7="","",COUNTIF('4 Extractions'!$E$5:$E$204,A7)) | T7: =IF(A7="","",IF(AND(F7<>"",G7<>"",H7<>"",I7<>"",N7<>"",O7<>"",P7<>"",OR(I7="Tracked today",I7="Can be tracked now",AND(K7<>"",L7<>""))),"Ready","Not ready"))
Q8: =IF(A8="","",COUNTIF('2 Tables'!$E$5:$E$204,"*"&A8&"*")) | R8: =IF(A8="","",COUNTIF('3 Fields'!$H$5:$H$204,A8)) | S8: =IF(A8="","",COUNTIF('4 Extractions'!$E$5:$E$204,A8)) | T8: =IF(A8="","",IF(AND(F8<>"",G8<>"",H8<>"",I8<>"",N8<>"",O8<>"",P8<>"",OR(I8="Tracked today",I8="Can be tracked now",AND(K8<>"",L8<>""))),"Ready","Not ready"))
Q9: =IF(A9="","",COUNTIF('2 Tables'!$E$5:$E$204,"*"&A9&"*")) | R9: =IF(A9="","",COUNTIF('3 Fields'!$H$5:$H$204,A9)) | S9: =IF(A9="","",COUNTIF('4 Extractions'!$E$5:$E$204,A9)) | T9: =IF(A9="","",IF(AND(F9<>"",G9<>"",H9<>"",I9<>"",N9<>"",O9<>"",P9<>"",OR(I9="Tracked today",I9="Can be tracked now",AND(K9<>"",L9<>""))),"Ready","Not ready"))
Q10: =IF(A10="","",COUNTIF('2 Tables'!$E$5:$E$204,"*"&A10&"*")) | R10: =IF(A10="","",COUNTIF('3 Fields'!$H$5:$H$204,A10)) | S10: =IF(A10="","",COUNTIF('4 Extractions'!$E$5:$E$204,A10)) | T10: =IF(A10="","",IF(AND(F10<>"",G10<>"",H10<>"",I10<>"",N10<>"",O10<>"",P10<>"",OR(I10="Tracked today",I10="Can be tracked now",AND(K10<>"",L10<>""))),"Ready","Not ready"))
Q11: =IF(A11="","",COUNTIF('2 Tables'!$E$5:$E$204,"*"&A11&"*")) | R11: =IF(A11="","",COUNTIF('3 Fields'!$H$5:$H$204,A11)) | S11: =IF(A11="","",COUNTIF('4 Extractions'!$E$5:$E$204,A11)) | T11: =IF(A11="","",IF(AND(F11<>"",G11<>"",H11<>"",I11<>"",N11<>"",O11<>"",P11<>"",OR(I11="Tracked today",I11="Can be tracked now",AND(K11<>"",L11<>""))),"Ready","Not ready"))
Q12: =IF(A12="","",COUNTIF('2 Tables'!$E$5:$E$204,"*"&A12&"*")) | R12: =IF(A12="","",COUNTIF('3 Fields'!$H$5:$H$204,A12)) | S12: =IF(A12="","",COUNTIF('4 Extractions'!$E$5:$E$204,A12)) | T12: =IF(A12="","",IF(AND(F12<>"",G12<>"",H12<>"",I12<>"",N12<>"",O12<>"",P12<>"",OR(I12="Tracked today",I12="Can be tracked now",AND(K12<>"",L12<>""))),"Ready","Not ready"))
Q13: =IF(A13="","",COUNTIF('2 Tables'!$E$5:$E$204,"*"&A13&"*")) | R13: =IF(A13="","",COUNTIF('3 Fields'!$H$5:$H$204,A13)) | S13: =IF(A13="","",COUNTIF('4 Extractions'!$E$5:$E$204,A13)) | T13: =IF(A13="","",IF(AND(F13<>"",G13<>"",H13<>"",I13<>"",N13<>"",O13<>"",P13<>"",OR(I13="Tracked today",I13="Can be tracked now",AND(K13<>"",L13<>""))),"Ready","Not ready"))
Q14: =IF(A14="","",COUNTIF('2 Tables'!$E$5:$E$204,"*"&A14&"*")) | R14: =IF(A14="","",COUNTIF('3 Fields'!$H$5:$H$204,A14)) | S14: =IF(A14="","",COUNTIF('4 Extractions'!$E$5:$E$204,A14)) | T14: =IF(A14="","",IF(AND(F14<>"",G14<>"",H14<>"",I14<>"",N14<>"",O14<>"",P14<>"",OR(I14="Tracked today",I14="Can be tracked now",AND(K14<>"",L14<>""))),"Ready","Not ready"))
Q15: =IF(A15="","",COUNTIF('2 Tables'!$E$5:$E$204,"*"&A15&"*")) | R15: =IF(A15="","",COUNTIF('3 Fields'!$H$5:$H$204,A15)) | S15: =IF(A15="","",COUNTIF('4 Extractions'!$E$5:$E$204,A15)) | T15: =IF(A15="","",IF(AND(F15<>"",G15<>"",H15<>"",I15<>"",N15<>"",O15<>"",P15<>"",OR(I15="Tracked today",I15="Can be tracked now",AND(K15<>"",L15<>""))),"Ready","Not ready"))
Q16: =IF(A16="","",COUNTIF('2 Tables'!$E$5:$E$204,"*"&A16&"*")) | R16: =IF(A16="","",COUNTIF('3 Fields'!$H$5:$H$204,A16)) | S16: =IF(A16="","",COUNTIF('4 Extractions'!$E$5:$E$204,A16)) | T16: =IF(A16="","",IF(AND(F16<>"",G16<>"",H16<>"",I16<>"",N16<>"",O16<>"",P16<>"",OR(I16="Tracked today",I16="Can be tracked now",AND(K16<>"",L16<>""))),"Ready","Not ready"))
Q17: =IF(A17="","",COUNTIF('2 Tables'!$E$5:$E$204,"*"&A17&"*")) | R17: =IF(A17="","",COUNTIF('3 Fields'!$H$5:$H$204,A17)) | S17: =IF(A17="","",COUNTIF('4 Extractions'!$E$5:$E$204,A17)) | T17: =IF(A17="","",IF(AND(F17<>"",G17<>"",H17<>"",I17<>"",N17<>"",O17<>"",P17<>"",OR(I17="Tracked today",I17="Can be tracked now",AND(K17<>"",L17<>""))),"Ready","Not ready"))
Q18: =IF(A18="","",COUNTIF('2 Tables'!$E$5:$E$204,"*"&A18&"*")) | R18: =IF(A18="","",COUNTIF('3 Fields'!$H$5:$H$204,A18)) | S18: =IF(A18="","",COUNTIF('4 Extractions'!$E$5:$E$204,A18)) | T18: =IF(A18="","",IF(AND(F18<>"",G18<>"",H18<>"",I18<>"",N18<>"",O18<>"",P18<>"",OR(I18="Tracked today",I18="Can be tracked now",AND(K18<>"",L18<>""))),"Ready","Not ready"))
... Q204: =IF(A204="","",COUNTIF('2 Tables'!$E$5:$E$204,"*"&A204&"*")) | R204: =IF(A204="","",COUNTIF('3 Fields'!$H$5:$H$204,A204)) | S204: =IF(A204="","",COUNTIF('4 Extractions'!$E$5:$E$204,A204)) | T204: =IF(A204="","",IF(AND(F204<>"",G204<>"",H204<>"",I204<>"",N204<>"",O204<>"",P204<>"",OR(I204="Tracked today",I204="Can be tracked now",AND(K204<>"",L204<>""))),"Ready","Not ready"))

Sheet Lists
A1: SourceType | B1: Structure | C1: ConnectionMethod | D1: YesNoNotSure | E1: Frequency | F1: Availability | G1: Provenance | H1: Kind | I1: UpdatePattern | J1: DataType | K1: FieldRole | L1: PersonalClass | M1: Required | N1: Priority | O1: TrackingStatus
A2: Database: Postgres | B2: Structured | C2: Direct database connection | D2: Yes | E2: Real time | F2: Available now | G2: Stated by a named person | H2: Table | I2: Full replace | J2: Text | K2: Measure | L2: Personal data | M2: Yes | N2: Must | O2: Tracked today
A3: Database: other | B3: Unstructured | C3: Scheduled file drop | D3: No | E3: Daily | F3: Can be made available | G3: Guessed | H3: File | I3: Append only | J3: Number | K3: Dimension | L3: Sensitive to the business | M3: No | N3: Should | O3: Can be tracked now
A4: Data warehouse | B4: Both | C4: File uploaded by the owner | D4: Not sure | E4: Weekly | F4: Planned | G4: Unknown | H4: Document type | I4: Changes only | J4: Date | K4: Date | L4: Neither | N4: Could | O4: Will be tracked in future
A5: File drop: CSV or Excel | C5: Email forwarded to us | E5: Monthly | F5: Not available | H5: Email type | I5: Not sure | J5: Date and time | K5: Key | L5: Not sure | N5: Not this time | O5: Cannot be tracked
A6: Email with attachment | C6: API | E6: Quarterly | J6: Yes or No | K6: Filter
A7: Document store: unstructured | C7: Manual, not yet decided | E7: Ad hoc | J7: Other | K7: Other
A8: Third-party portal or API
A9: Manual workbook (Excel)
A10: Other
